sphinx_copybutton/__init__.py
sphinx_copybutton/_static/check-solid.svg
sphinx_copybutton/_static/clipboard.min.js
sphinx_copybutton/_static/copy-button.svg
sphinx_copybutton/_static/copybutton.css
sphinx_copybutton/_static/copybutton.js_t
sphinx_copybutton/_static/copybutton_funcs.js
sphinx_copybutton-0.5.1.dist-info/LICENSE
sphinx_copybutton-0.5.1.dist-info/METADATA
sphinx_copybutton-0.5.1.dist-info/WHEEL
sphinx_copybutton-0.5.1.dist-info/top_level.txt
sphinx_copybutton-0.5.1.dist-info/RECORD
