Metadata-Version: 2.1
Name: sphinx-copybutton
Version: 0.5.1
Summary: Add a copy button to each of your code cells.
Home-page: https://github.com/executablebooks/sphinx-copybutton
Author: Executable Book Project
License: MIT License
Classifier: License :: OSI Approved :: MIT License
Classifier: Programming Language :: Python :: 3
Classifier: Programming Language :: Python :: 3.7
Classifier: Programming Language :: Python :: 3.8
Classifier: Programming Language :: Python :: 3.9
Classifier: Programming Language :: Python :: 3.10
Classifier: Programming Language :: Python :: 3 :: Only
Requires-Python: >=3.7
Provides-Extra: code_style
Provides-Extra: rtd
License-File: LICENSE
